scrapfly/__init__.py
scrapfly/api_config.py
scrapfly/api_response.py
scrapfly/client.py
scrapfly/errors.py
scrapfly/extraction_config.py
scrapfly/frozen_dict.py
scrapfly/scrape_config.py
scrapfly/screenshot_config.py
scrapfly/webhook.py
scrapfly/polyfill/__init__.py
scrapfly/polyfill/cached_property.py
scrapfly/reporter/ChainReporter.py
scrapfly/reporter/NoopReporter.py
scrapfly/reporter/PrintReporter.py
scrapfly/reporter/SentryReporter.py
scrapfly/reporter/__init__.py
scrapfly/scrapy/__init__.py
scrapfly/scrapy/downloader.py
scrapfly/scrapy/middleware.py
scrapfly/scrapy/pipelines.py
scrapfly/scrapy/request.py
scrapfly/scrapy/response.py
scrapfly/scrapy/spider.py
scrapfly_sdk-0.8.24.dist-info/licenses/LICENSE
scrapfly_sdk-0.8.24.dist-info/METADATA
scrapfly_sdk-0.8.24.dist-info/WHEEL
scrapfly_sdk-0.8.24.dist-info/top_level.txt
scrapfly_sdk-0.8.24.dist-info/RECORD
