Metadata-Version: 2.4
Name: scrapfly-sdk
Version: 0.8.24
Summary: Scrapfly SDK for Scrapfly
Home-page: https://github.com/scrapfly/python-sdk
Author: Scrapfly
Author-email: tech@scrapfly.io
License: BSD
Project-URL: Company, https://scrapfly.io
Project-URL: Documentation, https://scrapfly.io/docs
Project-URL: Source, https://github.com/scrapfly/python-sdk
Keywords: scraping,web scraping,data,extraction,scrapfly,sdk,cloud,scrapy
Classifier: Intended Audience :: Developers
Classifier: Programming Language :: Python
Classifier: Programming Language :: Python :: 3
Classifier: Programming Language :: Python :: 3.6
Classifier: Programming Language :: Python :: 3.7
Classifier: Programming Language :: Python :: 3.8
Classifier: Programming Language :: Python :: 3.9
Classifier: Programming Language :: Python :: 3.10
Classifier: Programming Language :: Python :: 3.11
Classifier: Programming Language :: Python :: 3 :: Only
Classifier: Topic :: Software Development :: Libraries :: Python Modules
Classifier: Topic :: Internet
Requires-Python: >=3.6
License-File: LICENSE
Requires-Dist: decorator>=4.2.0
Requires-Dist: requests>=2.25.0
Requires-Dist: python-dateutil<3.0.0,>=2.1
Requires-Dist: loguru>=0.5
Requires-Dist: urllib3>=1.26.0
Requires-Dist: backoff>=1.10.0
Provides-Extra: develop
Requires-Dist: bumpversion; extra == "develop"
Requires-Dist: isort; extra == "develop"
Requires-Dist: readme_renderer; extra == "develop"
Requires-Dist: twine; extra == "develop"
Requires-Dist: setuptools; extra == "develop"
Requires-Dist: wheel; extra == "develop"
Requires-Dist: pdoc3; extra == "develop"
Provides-Extra: deploy
Requires-Dist: bumpversion; extra == "deploy"
Requires-Dist: isort; extra == "deploy"
Requires-Dist: readme_renderer; extra == "deploy"
Requires-Dist: twine; extra == "deploy"
Requires-Dist: setuptools; extra == "deploy"
Requires-Dist: wheel; extra == "deploy"
Requires-Dist: pdoc3; extra == "deploy"
Requires-Dist: pip; extra == "deploy"
Requires-Dist: colorama; extra == "deploy"
Requires-Dist: sentry-sdk; extra == "deploy"
Provides-Extra: scrapy
Requires-Dist: scrapy>=2.4.0; extra == "scrapy"
Provides-Extra: parser
Requires-Dist: lxml; extra == "parser"
Requires-Dist: beautifulsoup4; extra == "parser"
Requires-Dist: soupsieve; extra == "parser"
Requires-Dist: extruct; extra == "parser"
Provides-Extra: speedups
Requires-Dist: brotlipy; extra == "speedups"
Requires-Dist: msgpack; extra == "speedups"
Provides-Extra: webhook-server
Requires-Dist: flask; extra == "webhook-server"
Provides-Extra: concurrency
Provides-Extra: all
Requires-Dist: soupsieve; extra == "all"
Requires-Dist: sentry-sdk; extra == "all"
Requires-Dist: twine; extra == "all"
Requires-Dist: msgpack; extra == "all"
Requires-Dist: flask; extra == "all"
Requires-Dist: setuptools; extra == "all"
Requires-Dist: readme_renderer; extra == "all"
Requires-Dist: beautifulsoup4; extra == "all"
Requires-Dist: isort; extra == "all"
Requires-Dist: extruct; extra == "all"
Requires-Dist: pip; extra == "all"
Requires-Dist: pdoc3; extra == "all"
Requires-Dist: lxml; extra == "all"
Requires-Dist: bumpversion; extra == "all"
Requires-Dist: scrapy>=2.4.0; extra == "all"
Requires-Dist: brotlipy; extra == "all"
Requires-Dist: colorama; extra == "all"
Requires-Dist: wheel; extra == "all"
Dynamic: author
Dynamic: author-email
Dynamic: classifier
Dynamic: description
Dynamic: description-content-type
Dynamic: home-page
Dynamic: keywords
Dynamic: license
Dynamic: license-file
Dynamic: project-url
Dynamic: provides-extra
Dynamic: requires-dist
Dynamic: requires-python
Dynamic: summary
